MANIFEST.in
account_tax.xml
account_tax_code.xml
l10n_pe_chart.xml
l10n_pe_wizard.xml
setup.py
./__init__.py
./__openerp__.py
i18n/ar.po
i18n/br.po
i18n/ca.po
i18n/de.po
i18n/es.po
i18n/es_PY.po
i18n/et.po
i18n/fr.po
i18n/gl.po
i18n/hu.po
i18n/it.po
i18n/l10n_pe.pot
i18n/nl.po
i18n/pt.po
i18n/pt_BR.po
i18n/ru.po
i18n/sl.po
i18n/sr@latin.po
i18n/sv.po
i18n/tr.po
images/config_chart_l10n_pe.jpeg
images/l10n_pe_chart.jpeg
openerp_l10n_pe.egg-info/PKG-INFO
openerp_l10n_pe.egg-info/SOURCES.txt
openerp_l10n_pe.egg-info/dependency_links.txt
openerp_l10n_pe.egg-info/requires.txt
openerp_l10n_pe.egg-info/top_level.txt
static/src/img/icon.png